skipnose/__init__.py
skipnose/skipnose.py
skipnose-0.3.1.dist-info/DESCRIPTION.rst
skipnose-0.3.1.dist-info/METADATA
skipnose-0.3.1.dist-info/RECORD
skipnose-0.3.1.dist-info/WHEEL
skipnose-0.3.1.dist-info/entry_points.txt
skipnose-0.3.1.dist-info/metadata.json
skipnose-0.3.1.dist-info/top_level.txt
