Metadata-Version: 2.0
Name: skipnose
Version: 0.3.1
Summary: Nose plugin which allows to include/exclude directories for testing by their glob pattern.
Home-page: https://github.com/Dealertrack/skipnose
Author: Miroslav Shubernetskiy
Author-email: UNKNOWN
License: UNKNOWN
Keywords: skipnose test nosetests nose nosetest
Platform: UNKNOWN
Classifier: License :: OSI Approved :: MIT License
Classifier: Programming Language :: Python
Classifier: Programming Language :: Python :: 3
Classifier: Development Status :: 4 - Beta
Classifier: Intended Audience :: Developers
Classifier: Topic :: Software Development :: Libraries :: Python Modules
Classifier: Topic :: Software Development :: Testing
Requires-Dist: nose
Requires-Dist: setuptools
